datastructures/App.py
Datastructures_Alex_Kaylyn-1.0.dist-info/METADATA
Datastructures_Alex_Kaylyn-1.0.dist-info/WHEEL
Datastructures_Alex_Kaylyn-1.0.dist-info/top_level.txt
Datastructures_Alex_Kaylyn-1.0.dist-info/RECORD
