Metadata-Version: 2.1
Name: Datastructures-Alex-Kaylyn
Version: 1.0
Summary: Data structures, linked lists, treestructures
Author: Alex McLean, Kaylyn Tanton
Author-email: alexander.mclean@ucalgary.ca, kaylyn.tanton@ucalgary.ca 
License: UNKNOWN
Platform: UNKNOWN
